{
  "positions":{
    "poses":{
      "pose":[{
        "reachPose":{
          "targetPose":{
            "x":0.38117900490760803,
            "y":0.0644112303853035,
            "z":0.22991076111793518,
            "thetaX":30.0,
            "thetaY":0.0,
            "thetaZ":-90.0

          },
          "constraint":{
            "speed":{
              "translation":0.30000001192092896,
              "orientation":0
            }
          }
        },
        "applicationData":"{\"kinova\":{\"color\":0}}",
        "handle":{
          "identifier":10051,
          "permission":7,
          "actionType":6
        },
        "name":"retracted_cart"
      }]
    }
  }
}